{
  "resources": [
    {
      "path": "data.csv",
      "name": "data",
      "profile": "tabular-data-resource",
      "scheme": "file",
      "format": "csv",
      "hashing": "md5",
      "encoding": "utf-8",
      "schema": {
        "fields": [
          {
            "name": "Edad",
            "type": "string",
            "constraints": {
              "enum": [
                "",
                "16 a 24",
                "25 a 29",
                "30 a 54",
                ">=55"
              ]
            },
            "title": "Edad"
          },
          {
            "name": "GeoCode",
            "type": "string",
            "title": "GeoCode"
          },
          {
            "name": "Sexo",
            "type": "string",
            "constraints": {
              "enum": [
                "",
                "Dona",
                "Home"
              ]
            },
            "title": "Sexo"
          },
          {
            "name": "Value",
            "type": "integer",
            "title": "Valor"
          },
          {
            "name": "Year",
            "type": "integer",
            "title": "Año"
          }
        ]
      }
    }
  ],
  "profile": "data-package",
  "name": "8-5-2",
  "title": "Tasa de desempleo, desglosada por sexo, edad y personas con discapacidad"
}